diff/__init__.py
diff/_diff.py
diff/py.typed
diff/unittest.py
diff/tests/__init__.py
diff/tests/test_diff.py
diff/tests/test_unittest.py
diff/tests/typing/__init__.py
diff/tests/typing/check_me_pyright.py
diff-2023.12.6.dist-info/METADATA
diff-2023.12.6.dist-info/WHEEL
diff-2023.12.6.dist-info/licenses/COPYING
diff-2023.12.6.dist-info/RECORD
