Metadata-Version: 2.1
Name: diff
Version: 2023.12.6
Summary: You diff objects, you find out why they ain't the same.
Project-URL: Documentation, https://diff.readthedocs.io/
Project-URL: Homepage, https://github.com/Julian/diff
Project-URL: Issues, https://github.com/Julian/diff/issues/
Project-URL: Funding, https://github.com/sponsors/Julian
Project-URL: Source, https://github.com/Julian/diff
Author: Julian Berman
Author-email: Julian+diff@GrayVines.com
License: MIT
License-File: COPYING
Keywords: diff,difference,protocol
Classifier: Development Status :: 3 - Alpha
Classifier: Intended Audience :: Developers
Classifier: License :: OSI Approved :: MIT License
Classifier: Operating System :: OS Independent
Classifier: Programming Language :: Python
Classifier: Programming Language :: Python :: 3.10
Classifier: Programming Language :: Python :: 3.11
Classifier: Programming Language :: Python :: 3.12
Classifier: Programming Language :: Python :: Implementation :: CPython
Classifier: Programming Language :: Python :: Implementation :: PyPy
Requires-Python: >=3.10
Requires-Dist: attrs>=23.1.0
